Metadata-Version: 1.2
Name: cbs-distributions
Version: 0.2
Summary: Gaussian distributions
Home-page: UNKNOWN
Author: CB
Author-email: hello@hello.org
License: BSD-3-Clause
Platform: UNKNOWN
Classifier: Programming Language :: Python :: 3
Requires-Python: >=3.6.3
